LICENSE
MANIFEST.in
README.md
setup.py
django_jp_stations.egg-info/PKG-INFO
django_jp_stations.egg-info/SOURCES.txt
django_jp_stations.egg-info/dependency_links.txt
django_jp_stations.egg-info/top_level.txt
docs/.keep
jp_stations/__init__.py
jp_stations/apps.py
jp_stations/managers.py
jp_stations/models.py
jp_stations/tests.py
jp_stations/fixtures/companies.json
jp_stations/fixtures/converted_companies.json
jp_stations/fixtures/converted_lines.json
jp_stations/fixtures/converted_stations.json
jp_stations/fixtures/lines.json
jp_stations/fixtures/stations.json
jp_stations/migrations/__init__.py