Metadata-Version: 1.1
Name: django-jp-stations
Version: 0.1
Summary: A simple Django app for japanese stations.
Home-page: https://github.com/t-hiroyoshi/django-jp-stations
Author: Hiroyoshi Takahashi
Author-email: t.hiroyoshi209@gmail.com
License: MIT License
Platform: UNKNOWN
Classifier: Environment :: Web Environment
Classifier: Framework :: Django
Classifier: Framework :: Django :: 1.11
Classifier: Intended Audience :: Developers
Classifier: Operating System :: OS Independent
Classifier: Programming Language :: Python
Classifier: Programming Language :: Python :: 3
Classifier: Programming Language :: Python :: 3.6
Classifier: Topic :: Internet :: WWW/HTTP
Classifier: Topic :: Internet :: WWW/HTTP :: Dynamic Content
